README.md
setup.py
CMD_Loading_Bar.egg-info/PKG-INFO
CMD_Loading_Bar.egg-info/SOURCES.txt
CMD_Loading_Bar.egg-info/dependency_links.txt
CMD_Loading_Bar.egg-info/top_level.txt
loading_bar/__init__.py
loading_bar/loadingbar.py