Metadata-Version: 2.1
Name: CMD-Loading-Bar
Version: 1.0.0
Summary: A simple yet elegant and feature rich cmd-line (stdout) loading bar.
Home-page: https://github.com/JoshWidrick/python-cmd-loading-bar
Author: Joshua Widrick
Author-email: jjwidric@buffalo.edu
License: MIT
Platform: UNKNOWN
